markitdown_sample_plugin/__about__.py
markitdown_sample_plugin/__init__.py
markitdown_sample_plugin/_plugin.py
markitdown_sample_plugin/py.typed
markitdown_sample_plugin-0.2.0a2.dist-info/METADATA
markitdown_sample_plugin-0.2.0a2.dist-info/WHEEL
markitdown_sample_plugin-0.2.0a2.dist-info/entry_points.txt
markitdown_sample_plugin-0.2.0a2.dist-info/RECORD
