Metadata-Version: 2.4
Name: markitdown-sample-plugin
Version: 0.2.0a2
Summary: A sample plugin for the "markitdown" library.
Project-URL: Documentation, https://github.com/microsoft/markitdown#readme
Project-URL: Issues, https://github.com/microsoft/markitdown/issues
Project-URL: Source, https://github.com/microsoft/markitdown
Author-email: Adam Fourney <adamfo@microsoft.com>
License-Expression: MIT
Classifier: Development Status :: 4 - Beta
Classifier: Programming Language :: Python
Classifier: Programming Language :: Python :: 3.10
Classifier: Programming Language :: Python :: 3.11
Classifier: Programming Language :: Python :: 3.12
Classifier: Programming Language :: Python :: 3.13
Classifier: Programming Language :: Python :: Implementation :: CPython
Classifier: Programming Language :: Python :: Implementation :: PyPy
Requires-Python: >=3.10
Requires-Dist: markitdown>=0.2.0a2
Requires-Dist: striprtf
